catscore/__init__.py
catscore/logger.py
catscore/session.py
catscore/time.py
kakaku_robot/__init__.py
kakaku_robot/main.py
kakaku_robot/model/__init__.py
kakaku_robot/model/item.py
kakaku_robot/site/__init__.py
kakaku_robot/site/ranking.py
tabelogrobot/__init__.py
tabelogrobot/main.py
tabelogrobot/model/__init__.py
tabelogrobot/model/item.py
tabelogrobot/model/ranking.py
tabelogrobot/site/__init__.py
tabelogrobot/site/detail.py
tabelogrobot/site/japan_ranking.py
tabelog_robot-0.1.3.dist-info/METADATA
tabelog_robot-0.1.3.dist-info/WHEEL
tabelog_robot-0.1.3.dist-info/entry_points.txt
tabelog_robot-0.1.3.dist-info/top_level.txt
tabelog_robot-0.1.3.dist-info/RECORD
