Metadata-Version: 2.1
Name: tabelog-robot
Version: 0.1.3
Summary: Scriping library for tabelog.com
Home-page: UNKNOWN
Author: rv
Author-email: yo-maruya@rescala.jp
License: MIT
Project-URL: Bug Reports, https://github.com/rv-rescala/catscore/issues
Project-URL: Source, https://github.com/rv-rescala/catscore
Keywords: crawler,scriping
Platform: UNKNOWN
Requires-Python: >=3.7
Requires-Dist: catscore
Requires-Dist: bs4
Requires-Dist: selenium
Requires-Dist: lxml
Requires-Dist: pandas
